rpipe/__init__.py
rpipe/py.typed
rpipe/client/__init__.py
rpipe/client/admin.py
rpipe/client/cli.py
rpipe/client/main.py
rpipe/client/client/__init__.py
rpipe/client/client/client.py
rpipe/client/client/crypt.py
rpipe/client/client/data.py
rpipe/client/client/delete.py
rpipe/client/client/errors.py
rpipe/client/client/io.py
rpipe/client/client/progress.py
rpipe/client/client/recv.py
rpipe/client/client/send.py
rpipe/client/client/util.py
rpipe/server/__init__.py
rpipe/server/app.py
rpipe/server/blocked.py
rpipe/server/main.py
rpipe/server/util.py
rpipe/server/admin/__init__.py
rpipe/server/admin/admin.py
rpipe/server/admin/uid.py
rpipe/server/admin/verify.py
rpipe/server/channel/__init__.py
rpipe/server/channel/channel.py
rpipe/server/channel/read.py
rpipe/server/channel/util.py
rpipe/server/channel/write.py
rpipe/server/server/__init__.py
rpipe/server/server/prune_thread.py
rpipe/server/server/server.py
rpipe/server/server/state.py
rpipe/server/server/stream.py
rpipe/shared/__init__.py
rpipe/shared/error_code.py
rpipe/shared/log.py
rpipe/shared/request_response.py
rpipe/shared/stats.py
rpipe/shared/util.py
rpipe/shared/version_.py
rpipe-11.1.0.dist-info/licenses/LICENSE
rpipe-11.1.0.dist-info/METADATA
rpipe-11.1.0.dist-info/WHEEL
rpipe-11.1.0.dist-info/entry_points.txt
rpipe-11.1.0.dist-info/top_level.txt
rpipe-11.1.0.dist-info/RECORD
