Metadata-Version: 2.4
Name: rpipe
Version: 11.1.0
Summary: A little python remote pipe server and client.
License: GPLv3
Project-URL: Homepage, https://github.com/zwimer/rpipe
Keywords: remote,pipe
Classifier: Programming Language :: Python :: 3
Classifier: Programming Language :: Python :: 3.14
Classifier: Development Status :: 5 - Production/Stable
Classifier: License :: OSI Approved :: GNU General Public License v3 (GPLv3)
Requires-Python: >=3.14
License-File: LICENSE
Requires-Dist: zstandard[cffi]
Requires-Dist: pycryptodomex
Requires-Dist: cryptography
Requires-Dist: argcomplete
Requires-Dist: requests
Requires-Dist: tqdm
Requires-Dist: zstdlib>=0.3.0
Requires-Dist: waitress
Requires-Dist: flask
Requires-Dist: human_readable
Requires-Dist: psutil
Dynamic: license-file
